Metadata-Version: 1.1
Name: django-social-widgets
Version: 0.2.1
Summary: Django app for easy embedding social network widgets and plugins into your site. Supports Facebook, Twitter, Google+, YouTube, Instagram and Pinterest.
Home-page: https://github.com/creafz/django-social-widgets
Author: Alex Parinov
Author-email: creafz@gmail.com
License: MIT License
Download-URL: https://github.com/creafz/django-social-widgets/tarball/0.2.1
Keywords: Django,social network,template,facebook,twitter
Platform: UNKNOWN
Classifier: Development Status :: 4 - Beta
Classifier: Environment :: Web Environment
Classifier: Framework :: Django
Classifier: Intended Audience :: Developers
Classifier: License :: OSI Approved :: MIT License
Classifier: Operating System :: OS Independent
Classifier: Programming Language :: Python
Classifier: Programming Language :: Python :: 2
Classifier: Programming Language :: Python :: 2.6
Classifier: Programming Language :: Python :: 2.7
Classifier: Topic :: Internet :: WWW/HTTP
Classifier: Topic :: Internet :: WWW/HTTP :: Dynamic Content
